opc/__init__.py
opc/base.py
opc/coreprops.py
opc/datetime.py
opc/package.py
opc/parser.py
opc/part.py
opc/rels.py
opc/relspart.py
opc/types.py
opc/uri.py
python_opc_lite-0.0.2.dist-info/LICENSE
python_opc_lite-0.0.2.dist-info/METADATA
python_opc_lite-0.0.2.dist-info/WHEEL
python_opc_lite-0.0.2.dist-info/top_level.txt
python_opc_lite-0.0.2.dist-info/RECORD
